ADNI_Part/run_adni.py
ADNI_Part/utils_adni.py
deprecated/for_chat.py
deprecated/gen copy.py
deprecated/generate_data copy.py
deprecated/mh copy 2.py
deprecated/mh copy.py
deprecated/mh_all_updates.py
deprecated/mh_known_theta_phi.py
deprecated/mh_with_labels_only.py
deprecated/mh_without_label_purely.py
deprecated/run copy 2.py
deprecated/run copy 3.py
deprecated/run copy.py
deprecated/run_with_labels_only.py
deprecated/run_without_label_purely.py
deprecated/test copy.py
deprecated/utils copy 2.py
deprecated/utils copy.py
deprecated/utils_with_labels_only.py
pysubebm/__init__.py
pysubebm/cross_validate.py
pysubebm/generate_data.py
pysubebm/mallows_hamming.py
pysubebm/mallows_kendall.py
pysubebm/mallows_model.py
pysubebm/mh.py
pysubebm/permutil.py
pysubebm/run.py
pysubebm/utils.py
pysubebm/viz.py
pysubebm/data/__init__.py
pysubebm/data/params.json
pysubebm/data/samples/10|100_0.csv
pysubebm/data/samples/5|50_0.csv
pysubebm/test/gen.py
pysubebm/test/test.py
pysubebm/test/test_sustain.py
pysubebm-0.3.8.dist-info/LICENSE
pysubebm-0.3.8.dist-info/METADATA
pysubebm-0.3.8.dist-info/WHEEL
pysubebm-0.3.8.dist-info/top_level.txt
pysubebm-0.3.8.dist-info/RECORD
